gsomos-1.0.1.dist-info/licenses/LICENSE
somos/__init__.py
somos/cosim.py
somos/io.py
somos/proj.py
somos/.ipynb_checkpoints/core-checkpoint.py
somos/.ipynb_checkpoints/cosim-checkpoint.py
somos/.ipynb_checkpoints/io-checkpoint.py
somos/.ipynb_checkpoints/proj-checkpoint.py
somos/__pycache__/__init__.cpython-311.pyc
somos/__pycache__/cosim.cpython-311.pyc
somos/__pycache__/io.cpython-311.pyc
somos/__pycache__/proj.cpython-311.pyc
somos/config/__init__.py
somos/config/tools4AS.css
somos/config/tools4AS.py
somos/config/tools4AS_ML.py
somos/config/tools4pyPC.py
somos/config/visualID_Eng-v0.py
somos/config/visualID_Eng.py
somos/config/.ipynb_checkpoints/tools4AS-checkpoint.py
somos/config/.ipynb_checkpoints/tools4pyPC-checkpoint.py
somos/config/.ipynb_checkpoints/visualID-checkpoint.py
somos/config/.ipynb_checkpoints/visualID_Eng-checkpoint.py
somos/config/__pycache__/Tools4PytChem.cpython-310.pyc
somos/config/__pycache__/__init__.cpython-311.pyc
somos/config/__pycache__/tools4AS.cpython-311.pyc
somos/config/__pycache__/tools4PytChem.cpython-310.pyc
somos/config/__pycache__/tools4PytChem.cpython-39.pyc
somos/config/__pycache__/tools4pyPC.cpython-310.pyc
somos/config/__pycache__/tools4pyPC.cpython-311.pyc
somos/config/__pycache__/tools4pyPC.cpython-39.pyc
somos/config/__pycache__/visualID.cpython-310.pyc
somos/config/__pycache__/visualID.cpython-311.pyc
somos/config/__pycache__/visualID.cpython-39.pyc
somos/config/__pycache__/visualID_Eng.cpython-310.pyc
somos/config/__pycache__/visualID_Eng.cpython-311.pyc
somos/config/__pycache__/visualID_Eng.cpython-39.pyc
somos/config/css/.directory
somos/config/css/visualID.css
somos/config/svg/Logo-Universite-Toulouse-n-2023.png
somos/config/svg/Python_logo_and_wordmark.svg.png
somos/config/svg/SOMOs_logo_vectorized.eps
somos/config/svg/SOMOs_logo_vectorized.png
somos/config/svg/SOMOs_logo_vectorized.svg
somos/config/svg/UT3_logoQ.jpg
somos/config/svg/UT3_logoQ.png
somos/config/svg/Universite-Toulouse-n-2023.svg
somos/config/svg/confidential.zip
gsomos-1.0.1.dist-info/METADATA
gsomos-1.0.1.dist-info/WHEEL
gsomos-1.0.1.dist-info/top_level.txt
gsomos-1.0.1.dist-info/RECORD
