Metadata-Version: 2.4
Name: gSOMOs
Version: 1.0.1
Summary: A Python package to analyze magnetic molecular orbitals (SOMOs) from Gaussian outputs
Author-email: "Romuald POTEAU, LPCNO" <romuald.poteau@univ-tlse3.fr>
Project-URL: Documentation, https://gsomos.readthedocs.io/
Project-URL: Repository, https://github.com/rpoteau/gSOMOs
Project-URL: Changelog, https://github.com/rpoteau/gSOMOs/blob/main/CHANGELOG.md
Requires-Python: >=3.8
License-File: LICENSE
Requires-Dist: cclib
Requires-Dist: numpy
Requires-Dist: pandas
Requires-Dist: matplotlib
Requires-Dist: seaborn
Requires-Dist: scipy
Requires-Dist: scikit-learn
Requires-Dist: ipywidgets
Requires-Dist: openpyxl
Requires-Dist: plotly
Requires-Dist: tqdm
Requires-Dist: jupyter
Provides-Extra: docs
Requires-Dist: sphinx; extra == "docs"
Requires-Dist: sphinx_rtd_theme; extra == "docs"
Requires-Dist: myst-parser; extra == "docs"
Requires-Dist: numpydoc; extra == "docs"
Dynamic: license-file
